ips_mace/__init__.py
ips_mace/mace_model.py
ips_mace/torch_d3.py
ips_mace-0.1.0.dist-info/LICENSE
ips_mace-0.1.0.dist-info/METADATA
ips_mace-0.1.0.dist-info/WHEEL
ips_mace-0.1.0.dist-info/RECORD
